rtl/hcpu_rom.v
// ============================================================================
// HCPU Master Table ROM — hcpu_rom.v
// 28 letters × 18 components × 8 bits = 28 × 144-bit entries
// Pre-unpacked from hm28.rom for single-cycle HLOAD
// (c) 2026 HMCL — HM-28-v1.2-HC18D
// ============================================================================
//
// Data source: data/hm28.json (SHA-256 sealed)
// Component layout: comp[i] = data_out[8*i +: 8]
//   comp[0]=Θ̂, comp[1]=Na, ..., comp[17]=Ψ
//
// Usage: addr = letter index (1–28), data_out = 144-bit codex vector
// Combinational read (no clock needed) for single-cycle HLOAD.
//

`include "hcpu_pkg.vh"

module hcpu_rom (
    input  wire [`ROM_ADDR_W-1:0]  addr,       // letter index (1–28)
    output reg  [`HREG_W-1:0]      data_out,   // 144-bit codex vector
    output reg                     valid       // 1 if addr in [1,28]
);

    // Component packing macro: {comp[17], comp[16], ..., comp[1], comp[0]}
    // So comp[i] = data_out[8*i +: 8]

    always @(*) begin
        valid = 1'b1;
        case (addr)
            // ── Index 1: Alif (ا) ──
            //  [Θ̂=0, Na=0, Nb=0, Nd=0, Kp=1, Kx=0, Ks=0, Ka=0, Kc=0,
            //   Qp=0, Qx=0, Qs=0, Qa=0, Qc=0, AN=0, AK=1, AQ=0, Ψ=0]
            5'd1:  data_out = {8'd0,8'd0,8'd1,8'd0,8'd0,8'd0,8'd0,8'd0,
                               8'd0,8'd0,8'd0,8'd0,8'd0,8'd1,8'd0,8'd0,
                               8'd0,8'd0};

            // ── Index 2: Ba (ب) ──
            //  [2,0,0,1,0,1,0,0,0,1,0,0,0,0,1,1,1,0]
            5'd2:  data_out = {8'd0,8'd1,8'd1,8'd1,8'd0,8'd0,8'd0,8'd0,
                               8'd1,8'd0,8'd0,8'd0,8'd1,8'd0,8'd1,8'd0,
                               8'd0,8'd2};

            // ── Index 3: Ta (ت) ──
            //  [2,2,0,0,0,1,0,0,0,1,0,0,0,0,2,1,1,0]
            5'd3:  data_out = {8'd0,8'd1,8'd1,8'd2,8'd0,8'd0,8'd0,8'd0,
                               8'd1,8'd0,8'd0,8'd0,8'd1,8'd0,8'd0,8'd0,
                               8'd2,8'd2};

            // ── Index 4: Tsa (ث) ──
            //  [2,3,0,0,0,1,0,0,0,1,0,0,0,0,3,1,1,0]
            5'd4:  data_out = {8'd0,8'd1,8'd1,8'd3,8'd0,8'd0,8'd0,8'd0,
                               8'd1,8'd0,8'd0,8'd0,8'd1,8'd0,8'd0,8'd0,
                               8'd3,8'd2};

            // ── Index 5: Jim (ج) ──
            //  [3,0,1,0,0,1,0,0,0,1,0,0,0,0,1,1,1,0]
            5'd5:  data_out = {8'd0,8'd1,8'd1,8'd1,8'd0,8'd0,8'd0,8'd0,
                               8'd1,8'd0,8'd0,8'd0,8'd1,8'd0,8'd0,8'd1,
                               8'd0,8'd3};

            // ── Index 6: Ha (ح) ──
            //  [3,0,0,0,0,1,0,0,0,1,0,0,0,0,0,1,1,0]
            5'd6:  data_out = {8'd0,8'd1,8'd1,8'd0,8'd0,8'd0,8'd0,8'd0,
                               8'd1,8'd0,8'd0,8'd0,8'd1,8'd0,8'd0,8'd0,
                               8'd0,8'd3};

            // ── Index 7: Kha (خ) ──
            //  [3,1,0,0,0,1,0,0,0,1,0,0,0,0,1,1,1,0]
            5'd7:  data_out = {8'd0,8'd1,8'd1,8'd1,8'd0,8'd0,8'd0,8'd0,
                               8'd1,8'd0,8'd0,8'd0,8'd1,8'd0,8'd0,8'd0,
                               8'd1,8'd3};

            // ── Index 8: Dal (د) ──
            //  [1,0,0,0,0,0,0,0,0,0,0,0,1,0,0,0,1,0]
            5'd8:  data_out = {8'd0,8'd1,8'd0,8'd0,8'd0,8'd1,8'd0,8'd0,
                               8'd0,8'd0,8'd0,8'd0,8'd0,8'd0,8'd0,8'd0,
                               8'd0,8'd1};

            // ── Index 9: Dzal (ذ) ──
            //  [1,1,0,0,0,0,0,0,0,0,0,0,1,0,1,0,1,0]
            5'd9:  data_out = {8'd0,8'd1,8'd0,8'd1,8'd0,8'd1,8'd0,8'd0,
                               8'd0,8'd0,8'd0,8'd0,8'd0,8'd0,8'd0,8'd0,
                               8'd1,8'd1};

            // ── Index 10: Ra (ر) ──
            //  [1,0,0,0,0,0,0,0,0,0,0,1,0,0,0,0,1,0]
            5'd10: data_out = {8'd0,8'd1,8'd0,8'd0,8'd0,8'd0,8'd1,8'd0,
                               8'd0,8'd0,8'd0,8'd0,8'd0,8'd0,8'd0,8'd0,
                               8'd0,8'd1};

            // ── Index 11: Zay (ز) ──
            //  [1,1,0,0,0,0,0,0,0,0,0,1,0,0,1,0,1,0]
            5'd11: data_out = {8'd0,8'd1,8'd0,8'd1,8'd0,8'd0,8'd1,8'd0,
                               8'd0,8'd0,8'd0,8'd0,8'd0,8'd0,8'd0,8'd0,
                               8'd1,8'd1};

            // ── Index 12: Sin (س) ──
            //  [4,0,0,0,0,0,0,0,0,1,2,0,0,0,0,0,3,0]
            5'd12: data_out = {8'd0,8'd3,8'd0,8'd0,8'd0,8'd0,8'd0,8'd2,
                               8'd1,8'd0,8'd0,8'd0,8'd0,8'd0,8'd0,8'd0,
                               8'd0,8'd4};

            // ── Index 13: Syin (ش) ──
            //  [4,3,0,0,0,0,0,0,0,1,2,0,0,0,3,0,3,0]
            5'd13: data_out = {8'd0,8'd3,8'd0,8'd3,8'd0,8'd0,8'd0,8'd2,
                               8'd1,8'd0,8'd0,8'd0,8'd0,8'd0,8'd0,8'd0,
                               8'd3,8'd4};

            // ── Index 14: Shad (ص) ──
            //  [6,0,0,0,0,0,0,0,0,1,0,0,0,1,0,0,2,0]
            5'd14: data_out = {8'd0,8'd2,8'd0,8'd0,8'd1,8'd0,8'd0,8'd0,
                               8'd1,8'd0,8'd0,8'd0,8'd0,8'd0,8'd0,8'd0,
                               8'd0,8'd6};

            // ── Index 15: Dhad (ض) ──
            //  [6,1,0,0,0,0,0,0,0,1,0,0,0,1,1,0,2,0]
            5'd15: data_out = {8'd0,8'd2,8'd0,8'd1,8'd1,8'd0,8'd0,8'd0,
                               8'd1,8'd0,8'd0,8'd0,8'd0,8'd0,8'd0,8'd0,
                               8'd1,8'd6};

            // ── Index 16: Tha (ط) ──
            //  [4,0,0,0,0,0,1,0,0,0,0,0,0,1,0,1,1,0]
            5'd16: data_out = {8'd0,8'd1,8'd1,8'd0,8'd1,8'd0,8'd0,8'd0,
                               8'd0,8'd0,8'd0,8'd1,8'd0,8'd0,8'd0,8'd0,
                               8'd0,8'd4};

            // ── Index 17: Zha (ظ) ──
            //  [4,1,0,0,0,0,1,0,0,0,0,0,0,1,1,1,1,0]
            5'd17: data_out = {8'd0,8'd1,8'd1,8'd1,8'd1,8'd0,8'd0,8'd0,
                               8'd0,8'd0,8'd0,8'd1,8'd0,8'd0,8'd0,8'd0,
                               8'd1,8'd4};

            // ── Index 18: Ain (ع) ──
            //  [3,0,0,0,0,0,0,0,0,1,1,0,0,0,0,0,2,0]
            5'd18: data_out = {8'd0,8'd2,8'd0,8'd0,8'd0,8'd0,8'd0,8'd1,
                               8'd1,8'd0,8'd0,8'd0,8'd0,8'd0,8'd0,8'd0,
                               8'd0,8'd3};

            // ── Index 19: Ghain (غ) ──
            //  [3,1,0,0,0,0,0,0,0,1,1,0,0,0,1,0,2,0]
            5'd19: data_out = {8'd0,8'd2,8'd0,8'd1,8'd0,8'd0,8'd0,8'd1,
                               8'd1,8'd0,8'd0,8'd0,8'd0,8'd0,8'd0,8'd0,
                               8'd1,8'd3};

            // ── Index 20: Fa (ف) ──
            //  [5,1,0,0,0,1,0,0,0,1,0,0,0,1,1,1,2,0]
            5'd20: data_out = {8'd0,8'd2,8'd1,8'd1,8'd1,8'd0,8'd0,8'd0,
                               8'd1,8'd0,8'd0,8'd0,8'd1,8'd0,8'd0,8'd0,
                               8'd1,8'd5};

            // ── Index 21: Qaf (ق) ──
            //  [6,2,0,0,0,0,0,0,0,1,0,0,0,1,2,0,2,0]
            5'd21: data_out = {8'd0,8'd2,8'd0,8'd2,8'd1,8'd0,8'd0,8'd0,
                               8'd1,8'd0,8'd0,8'd0,8'd0,8'd0,8'd0,8'd0,
                               8'd2,8'd6};

            // ── Index 22: Kaf (ك) ──
            //  [2,0,0,0,0,0,0,1,0,0,0,0,0,0,0,1,0,1]
            5'd22: data_out = {8'd1,8'd0,8'd1,8'd0,8'd0,8'd0,8'd0,8'd0,
                               8'd0,8'd0,8'd1,8'd0,8'd0,8'd0,8'd0,8'd0,
                               8'd0,8'd2};

            // ── Index 23: Lam (ل) ──
            //  [1,0,0,0,0,1,0,0,0,1,0,0,0,0,0,1,1,0]
            5'd23: data_out = {8'd0,8'd1,8'd1,8'd0,8'd0,8'd0,8'd0,8'd0,
                               8'd1,8'd0,8'd0,8'd0,8'd1,8'd0,8'd0,8'd0,
                               8'd0,8'd1};

            // ── Index 24: Mim (م) ──
            //  [4,0,0,0,0,0,0,0,1,0,0,0,0,1,0,1,1,0]
            5'd24: data_out = {8'd0,8'd1,8'd1,8'd0,8'd1,8'd0,8'd0,8'd0,
                               8'd0,8'd1,8'd0,8'd0,8'd0,8'd0,8'd0,8'd0,
                               8'd0,8'd4};

            // ── Index 25: Nun (ن) ──
            //  [2,1,0,0,0,0,0,0,0,1,0,0,0,0,1,0,1,0]
            5'd25: data_out = {8'd0,8'd1,8'd0,8'd1,8'd0,8'd0,8'd0,8'd0,
                               8'd1,8'd0,8'd0,8'd0,8'd0,8'd0,8'd0,8'd0,
                               8'd1,8'd2};

            // ── Index 26: Waw (و) ──
            //  [5,0,0,0,0,0,0,0,0,0,0,1,0,1,0,0,2,0]
            5'd26: data_out = {8'd0,8'd2,8'd0,8'd0,8'd1,8'd0,8'd1,8'd0,
                               8'd0,8'd0,8'd0,8'd0,8'd0,8'd0,8'd0,8'd0,
                               8'd0,8'd5};

            // ── Index 27: Haa (هـ) ──
            //  [8,0,0,0,0,0,0,0,1,0,0,0,0,2,0,1,2,0]
            5'd27: data_out = {8'd0,8'd2,8'd1,8'd0,8'd2,8'd0,8'd0,8'd0,
                               8'd0,8'd1,8'd0,8'd0,8'd0,8'd0,8'd0,8'd0,
                               8'd0,8'd8};

            // ── Index 28: Ya (ي) ──
            //  [3,0,0,2,0,0,0,0,0,1,1,0,0,0,2,0,2,0]
            5'd28: data_out = {8'd0,8'd2,8'd0,8'd2,8'd0,8'd0,8'd0,8'd1,
                               8'd1,8'd0,8'd0,8'd0,8'd0,8'd0,8'd2,8'd0,
                               8'd0,8'd3};

            // ── Index 31: Test Negative (Corrupt Vector) ──
            // Intentionally fails G4 (Theta=1, Qc=2 -> U=8. 1 >= 8 is FALSE)
            // Used strictly for Hardware Pipeline Validation checks.
            5'd31: data_out = {8'd0,8'd0,8'd0,8'd0,8'd0,8'd0,8'd0,8'd0,
                               8'd0,8'd0,8'd0,8'd0,8'd0,8'd2,8'd0,8'd0,
                               8'd0,8'd1};

            default: begin
                data_out = {`HREG_W{1'b0}};
                valid    = 1'b0;
            end
        endcase
    end

endmodule

rtl/tb/tb_rom.v
// ============================================================================
// Testbench: Master Table ROM — tb_rom.v
// Verifies all 28 letter vectors match hm28.json golden values
// (c) 2026 HMCL
// ============================================================================

`timescale 1ns/1ps
`include "hcpu_pkg.vh"

module tb_rom;

    reg  [`ROM_ADDR_W-1:0] addr;
    wire [`HREG_W-1:0]     data_out;
    wire                   valid;

    hcpu_rom uut (
        .addr     (addr),
        .data_out (data_out),
        .valid    (valid)
    );

    // Extract component from 144-bit vector
    `define COMP(vec, idx) vec[8*(idx) +: 8]

    integer pass_count;
    integer fail_count;
    integer i;

    // Task to check one letter
    task check_letter;
        input [4:0]  index;
        input [7:0]  exp_theta, exp_na, exp_nb, exp_nd;
        input [7:0]  exp_kp, exp_kx, exp_ks, exp_ka, exp_kc;
        input [7:0]  exp_qp, exp_qx, exp_qs, exp_qa, exp_qc;
        input [7:0]  exp_an, exp_ak, exp_aq, exp_psi;
        begin
            addr = index;
            #1;
            if (!valid) begin
                $display("FAIL: Index %0d — invalid address", index);
                fail_count = fail_count + 1;
            end else if (
                `COMP(data_out, 0)  == exp_theta &&
                `COMP(data_out, 1)  == exp_na    &&
                `COMP(data_out, 2)  == exp_nb    &&
                `COMP(data_out, 3)  == exp_nd    &&
                `COMP(data_out, 4)  == exp_kp    &&
                `COMP(data_out, 5)  == exp_kx    &&
                `COMP(data_out, 6)  == exp_ks    &&
                `COMP(data_out, 7)  == exp_ka    &&
                `COMP(data_out, 8)  == exp_kc    &&
                `COMP(data_out, 9)  == exp_qp    &&
                `COMP(data_out, 10) == exp_qx    &&
                `COMP(data_out, 11) == exp_qs    &&
                `COMP(data_out, 12) == exp_qa    &&
                `COMP(data_out, 13) == exp_qc    &&
                `COMP(data_out, 14) == exp_an    &&
                `COMP(data_out, 15) == exp_ak    &&
                `COMP(data_out, 16) == exp_aq    &&
                `COMP(data_out, 17) == exp_psi
            ) begin
                $display("PASS: Index %0d", index);
                pass_count = pass_count + 1;
            end else begin
                $display("FAIL: Index %0d", index);
                $display("  Got:    [%0d,%0d,%0d,%0d,%0d,%0d,%0d,%0d,%0d,%0d,%0d,%0d,%0d,%0d,%0d,%0d,%0d,%0d]",
                    `COMP(data_out,0), `COMP(data_out,1), `COMP(data_out,2),
                    `COMP(data_out,3), `COMP(data_out,4), `COMP(data_out,5),
                    `COMP(data_out,6), `COMP(data_out,7), `COMP(data_out,8),
                    `COMP(data_out,9), `COMP(data_out,10),`COMP(data_out,11),
                    `COMP(data_out,12),`COMP(data_out,13),`COMP(data_out,14),
                    `COMP(data_out,15),`COMP(data_out,16),`COMP(data_out,17));
                $display("  Expect: [%0d,%0d,%0d,%0d,%0d,%0d,%0d,%0d,%0d,%0d,%0d,%0d,%0d,%0d,%0d,%0d,%0d,%0d]",
                    exp_theta, exp_na, exp_nb, exp_nd,
                    exp_kp, exp_kx, exp_ks, exp_ka, exp_kc,
                    exp_qp, exp_qx, exp_qs, exp_qa, exp_qc,
                    exp_an, exp_ak, exp_aq, exp_psi);
                fail_count = fail_count + 1;
            end
        end
    endtask

    initial begin
        $dumpfile("tb_rom.vcd");
        $dumpvars(0, tb_rom);

        pass_count = 0;
        fail_count = 0;

        $display("=== HCPU ROM Verification (28 letters) ===");

        //                    idx  Θ  Na Nb Nd Kp Kx Ks Ka Kc Qp Qx Qs Qa Qc AN AK AQ  Ψ
        check_letter( 5'd1,   0, 0, 0, 0, 1, 0, 0, 0, 0, 0, 0, 0, 0, 0, 0, 1, 0, 0); // Alif
        check_letter( 5'd2,   2, 0, 0, 1, 0, 1, 0, 0, 0, 1, 0, 0, 0, 0, 1, 1, 1, 0); // Ba
        check_letter( 5'd3,   2, 2, 0, 0, 0, 1, 0, 0, 0, 1, 0, 0, 0, 0, 2, 1, 1, 0); // Ta
        check_letter( 5'd4,   2, 3, 0, 0, 0, 1, 0, 0, 0, 1, 0, 0, 0, 0, 3, 1, 1, 0); // Tsa
        check_letter( 5'd5,   3, 0, 1, 0, 0, 1, 0, 0, 0, 1, 0, 0, 0, 0, 1, 1, 1, 0); // Jim
        check_letter( 5'd6,   3, 0, 0, 0, 0, 1, 0, 0, 0, 1, 0, 0, 0, 0, 0, 1, 1, 0); // Ha
        check_letter( 5'd7,   3, 1, 0, 0, 0, 1, 0, 0, 0, 1, 0, 0, 0, 0, 1, 1, 1, 0); // Kha
        check_letter( 5'd8,   1, 0, 0, 0, 0, 0, 0, 0, 0, 0, 0, 0, 1, 0, 0, 0, 1, 0); // Dal
        check_letter( 5'd9,   1, 1, 0, 0, 0, 0, 0, 0, 0, 0, 0, 0, 1, 0, 1, 0, 1, 0); // Dzal
        check_letter(5'd10,   1, 0, 0, 0, 0, 0, 0, 0, 0, 0, 0, 1, 0, 0, 0, 0, 1, 0); // Ra
        check_letter(5'd11,   1, 1, 0, 0, 0, 0, 0, 0, 0, 0, 0, 1, 0, 0, 1, 0, 1, 0); // Zay
        check_letter(5'd12,   4, 0, 0, 0, 0, 0, 0, 0, 0, 1, 2, 0, 0, 0, 0, 0, 3, 0); // Sin
        check_letter(5'd13,   4, 3, 0, 0, 0, 0, 0, 0, 0, 1, 2, 0, 0, 0, 3, 0, 3, 0); // Syin
        check_letter(5'd14,   6, 0, 0, 0, 0, 0, 0, 0, 0, 1, 0, 0, 0, 1, 0, 0, 2, 0); // Shad
        check_letter(5'd15,   6, 1, 0, 0, 0, 0, 0, 0, 0, 1, 0, 0, 0, 1, 1, 0, 2, 0); // Dhad
        check_letter(5'd16,   4, 0, 0, 0, 0, 0, 1, 0, 0, 0, 0, 0, 0, 1, 0, 1, 1, 0); // Tha
        check_letter(5'd17,   4, 1, 0, 0, 0, 0, 1, 0, 0, 0, 0, 0, 0, 1, 1, 1, 1, 0); // Zha
        check_letter(5'd18,   3, 0, 0, 0, 0, 0, 0, 0, 0, 1, 1, 0, 0, 0, 0, 0, 2, 0); // Ain
        check_letter(5'd19,   3, 1, 0, 0, 0, 0, 0, 0, 0, 1, 1, 0, 0, 0, 1, 0, 2, 0); // Ghain
        check_letter(5'd20,   5, 1, 0, 0, 0, 1, 0, 0, 0, 1, 0, 0, 0, 1, 1, 1, 2, 0); // Fa
        check_letter(5'd21,   6, 2, 0, 0, 0, 0, 0, 0, 0, 1, 0, 0, 0, 1, 2, 0, 2, 0); // Qaf
        check_letter(5'd22,   2, 0, 0, 0, 0, 0, 0, 1, 0, 0, 0, 0, 0, 0, 0, 1, 0, 1); // Kaf
        check_letter(5'd23,   1, 0, 0, 0, 0, 1, 0, 0, 0, 1, 0, 0, 0, 0, 0, 1, 1, 0); // Lam
        check_letter(5'd24,   4, 0, 0, 0, 0, 0, 0, 0, 1, 0, 0, 0, 0, 1, 0, 1, 1, 0); // Mim
        check_letter(5'd25,   2, 1, 0, 0, 0, 0, 0, 0, 0, 1, 0, 0, 0, 0, 1, 0, 1, 0); // Nun
        check_letter(5'd26,   5, 0, 0, 0, 0, 0, 0, 0, 0, 0, 0, 1, 0, 1, 0, 0, 2, 0); // Waw
        check_letter(5'd27,   8, 0, 0, 0, 0, 0, 0, 0, 1, 0, 0, 0, 0, 2, 0, 1, 2, 0); // Haa
        check_letter(5'd28,   3, 0, 0, 2, 0, 0, 0, 0, 0, 1, 1, 0, 0, 0, 2, 0, 2, 0); // Ya

        // Invalid address test
        addr = 5'd0;  #1;
        if (!valid) begin
            $display("PASS: Index 0 — correctly invalid");
            pass_count = pass_count + 1;
        end else begin
            $display("FAIL: Index 0 should be invalid");
            fail_count = fail_count + 1;
        end

        addr = 5'd29; #1;
        if (!valid) begin
            $display("PASS: Index 29 — correctly invalid");
            pass_count = pass_count + 1;
        end else begin
            $display("FAIL: Index 29 should be invalid");
            fail_count = fail_count + 1;
        end

        $display("=====================================");
        $display("ROM Tests: %0d PASS, %0d FAIL", pass_count, fail_count);
        $display("=====================================");

        // $finish(1) sets the diagnostic message level, not the exit status —
        // vvp still returns 0, so a failing run would look green to CI.
        // $fatal is what actually exits non-zero.
        if (fail_count > 0) $fatal(1, "%0d test(s) FAILED", fail_count);
        else $finish(0);
    end

endmodule

rtl/tb/tb_rom.vcd
$date
	Sun Aug 23 03:56:16 2026
$end
$version
	Icarus Verilog
$end
$timescale
	1ps
$end
$scope module tb_rom $end
$var wire 1 ! valid $end
$var wire 144 " data_out [143:0] $end
$var reg 5 # addr [4:0] $end
$var integer 32 $ fail_count [31:0] $end
$var integer 32 % pass_count [31:0] $end
$scope module uut $end
$var wire 5 & addr [4:0] $end
$var reg 144 ' data_out [143:0] $end
$var reg 1 ! valid $end
$upscope $end
$scope task check_letter $end
$var reg 8 ( exp_ak [7:0] $end
$var reg 8 ) exp_an [7:0] $end
$var reg 8 * exp_aq [7:0] $end
$var reg 8 + exp_ka [7:0] $end
$var reg 8 , exp_kc [7:0] $end
$var reg 8 - exp_kp [7:0] $end
$var reg 8 . exp_ks [7:0] $end
$var reg 8 / exp_kx [7:0] $end
$var reg 8 0 exp_na [7:0] $end
$var reg 8 1 exp_nb [7:0] $end
$var reg 8 2 exp_nd [7:0] $end
$var reg 8 3 exp_psi [7:0] $end
$var reg 8 4 exp_qa [7:0] $end
$var reg 8 5 exp_qc [7:0] $end
$var reg 8 6 exp_qp [7:0] $end
$var reg 8 7 exp_qs [7:0] $end
$var reg 8 8 exp_qx [7:0] $end
$var reg 8 9 exp_theta [7:0] $end
$var reg 5 : index [4:0] $end
$upscope $end
$upscope $end
$enddefinitions $end
$comment Show the parameter values. $end
$dumpall
$end
#0
$dumpvars
b1 :
b0 9
b0 8
b0 7
b0 6
b0 5
b0 4
b0 3
b0 2
b0 1
b0 0
b0 /
b0 .
b1 -
b0 ,
b0 +
b0 *
b0 )
b1 (
b1000000000000000000000000000000000000000000000000000000000000000000000000000000000000000100000000000000000000000000000000 '
b1 &
b0 %
b0 $
b1 #
b1000000000000000000000000000000000000000000000000000000000000000000000000000000000000000100000000000000000000000000000000 "
1!
$end
#1000
b100000001000000010000000000000000000000000000000000000001000000000000000000000000000000010000000000000001000000000000000000000010 "
b100000001000000010000000000000000000000000000000000000001000000000000000000000000000000010000000000000001000000000000000000000010 '
b10 #
b10 &
b1 *
b1 )
b1 6
b1 /
b0 -
b1 2
b10 9
b10 :
b1 %
#2000
b100000001000000100000000000000000000000000000000000000001000000000000000000000000000000010000000000000000000000000000001000000010 "
b100000001000000100000000000000000000000000000000000000001000000000000000000000000000000010000000000000000000000000000001000000010 '
b11 #
b11 &
b10 )
b0 2
b10 0
b11 :
b10 %
#3000
b100000001000000110000000000000000000000000000000000000001000000000000000000000000000000010000000000000000000000000000001100000010 "
b100000001000000110000000000000000000000000000000000000001000000000000000000000000000000010000000000000000000000000000001100000010 '
b100 #
b100 &
b11 )
b11 0
b100 :
b11 %
#4000
b100000001000000010000000000000000000000000000000000000001000000000000000000000000000000010000000000000000000000010000000000000011 "
b100000001000000010000000000000000000000000000000000000001000000000000000000000000000000010000000000000000000000010000000000000011 '
b101 #
b101 &
b1 )
b1 1
b0 0
b11 9
b101 :
b100 %
#5000
b100000001000000000000000000000000000000000000000000000001000000000000000000000000000000010000000000000000000000000000000000000011 "
b100000001000000000000000000000000000000000000000000000001000000000000000000000000000000010000000000000000000000000000000000000011 '
b110 #
b110 &
b0 )
b0 1
b110 :
b101 %
#6000
b100000001000000010000000000000000000000000000000000000001000000000000000000000000000000010000000000000000000000000000000100000011 "
b100000001000000010000000000000000000000000000000000000001000000000000000000000000000000010000000000000000000000000000000100000011 '
b111 #
b111 &
b1 )
b1 0
b111 :
b110 %
#7000
b100000000000000000000000000000001000000000000000000000000000000000000000000000000000000000000000000000000000000000000000000000001 "
b100000000000000000000000000000001000000000000000000000000000000000000000000000000000000000000000000000000000000000000000000000001 '
b1000 #
b1000 &
b0 (
b0 )
b1 4
b0 6
b0 /
b0 0
b1 9
b1000 :
b111 %
#8000
b100000000000000010000000000000001000000000000000000000000000000000000000000000000000000000000000000000000000000000000000100000001 "
b100000000000000010000000000000001000000000000000000000000000000000000000000000000000000000000000000000000000000000000000100000001 '
b1001 #
b1001 &
b1 )
b1 0
b1001 :
b1000 %
#9000
b100000000000000000000000000000000000000010000000000000000000000000000000000000000000000000000000000000000000000000000000000000001 "
b100000000000000000000000000000000000000010000000000000000000000000000000000000000000000000000000000000000000000000000000000000001 '
b1010 #
b1010 &
b0 )
b0 4
b1 7
b0 0
b1010 :
b1001 %
#10000
b100000000000000010000000000000000000000010000000000000000000000000000000000000000000000000000000000000000000000000000000100000001 "
b100000000000000010000000000000000000000010000000000000000000000000000000000000000000000000000000000000000000000000000000100000001 '
b1011 #
b1011 &
b1 )
b1 0
b1011 :
b1010 %
#11000
b1100000000000000000000000000000000000000000000001000000001000000000000000000000000000000000000000000000000000000000000000000000100 "
b1100000000000000000000000000000000000000000000001000000001000000000000000000000000000000000000000000000000000000000000000000000100 '
b1100 #
b1100 &
b11 *
b0 )
b0 7
b10 8
b1 6
b0 0
b100 9
b1100 :
b1011 %
#12000
b1100000000000000110000000000000000000000000000001000000001000000000000000000000000000000000000000000000000000000000000001100000100 "
b1100000000000000110000000000000000000000000000001000000001000000000000000000000000000000000000000000000000000000000000001100000100 '
b1101 #
b1101 &
b11 )
b11 0
b1101 :
b1100 %
#13000
b1000000000000000000000000100000000000000000000000000000001000000000000000000000000000000000000000000000000000000000000000000000110 "
b1000000000000000000000000100000000000000000000000000000001000000000000000000000000000000000000000000000000000000000000000000000110 '
b1110 #
b1110 &
b10 *
b0 )
b1 5
b0 8
b0 0
b110 9
b1110 :
b1101 %
#14000
b1000000000000000010000000100000000000000000000000000000001000000000000000000000000000000000000000000000000000000000000000100000110 "
b1000000000000000010000000100000000000000000000000000000001000000000000000000000000000000000000000000000000000000000000000100000110 '
b1111 #
b1111 &
b1 )
b1 0
b1111 :
b1110 %
#15000
b100000001000000000000000100000000000000000000000000000000000000000000000100000000000000000000000000000000000000000000000000000100 "
b100000001000000000000000100000000000000000000000000000000000000000000000100000000000000000000000000000000000000000000000000000100 '
b10000 #
b10000 &
b1 *
b1 (
b0 )
b0 6
b1 +
b0 0
b100 9
b10000 :
b1111 %
#16000
b100000001000000010000000100000000000000000000000000000000000000000000000100000000000000000000000000000000000000000000000100000100 "
b100000001000000010000000100000000000000000000000000000000000000000000000100000000000000000000000000000000000000000000000100000100 '
b10001 #
b10001 &
b1 )
b1 0
b10001 :
b10000 %
#17000
b1000000000000000000000000000000000000000000000000100000001000000000000000000000000000000000000000000000000000000000000000000000011 "
b1000000000000000000000000000000000000000000000000100000001000000000000000000000000000000000000000000000000000000000000000000000011 '
b10010 #
b10010 &
b10 *
b0 (
b0 )
b0 5
b1 8
b1 6
b0 +
b0 0
b11 9
b10010 :
b10001 %
#18000
b1000000000000000010000000000000000000000000000000100000001000000000000000000000000000000000000000000000000000000000000000100000011 "
b1000000000000000010000000000000000000000000000000100000001000000000000000000000000000000000000000000000000000000000000000100000011 '
b10011 #
b10011 &
b1 )
b1 0
b10011 :
b10010 %
#19000
b1000000001000000010000000100000000000000000000000000000001000000000000000000000000000000010000000000000000000000000000000100000101 "
b1000000001000000010000000100000000000000000000000000000001000000000000000000000000000000010000000000000000000000000000000100000101 '
b10100 #
b10100 &
b1 (
b1 5
b0 8
b1 /
b101 9
b10100 :
b10011 %
#20000
b1000000000000000100000000100000000000000000000000000000001000000000000000000000000000000000000000000000000000000000000001000000110 "
b1000000000000000100000000100000000000000000000000000000001000000000000000000000000000000000000000000000000000000000000001000000110 '
b10101 #
b10101 &
b0 (
b10 )
b0 /
b10 0
b110 9
b10101 :
b10100 %
#21000
b10000000000000001000000000000000000000000000000000000000000000000000000010000000000000000000000000000000000000000000000000000000000000010 "
b10000000000000001000000000000000000000000000000000000000000000000000000010000000000000000000000000000000000000000000000000000000000000010 '
b10110 #
b10110 &
b1 3
b0 *
b1 (
b0 )
b0 5
b0 6
b1 ,
b0 0
b10 9
b10110 :
b10101 %
#22000
b100000001000000000000000000000000000000000000000000000001000000000000000000000000000000010000000000000000000000000000000000000001 "
b100000001000000000000000000000000000000000000000000000001000000000000000000000000000000010000000000000000000000000000000000000001 '
b10111 #
b10111 &
b0 3
b1 *
b1 6
b0 ,
b1 /
b1 9
b10111 :
b10110 %
#23000
b100000001000000000000000100000000000000000000000000000000000000010000000000000000000000000000000000000000000000000000000000000100 "
b100000001000000000000000100000000000000000000000000000000000000010000000000000000000000000000000000000000000000000000000000000100 '
b11000 #
b11000 &
b1 5
b0 6
b1 ,
b0 /
b100 9
b11000 :
b10111 %
#24000
b100000001000000010000000000000000000000000000000000000001000000000000000000000000000000010000000000000000000000000000000100000010 "
b100000001000000010000000000000000000000000000000000000001000000000000000000000000000000010000000000000000000000000000000100000010 '
b11001 #
b11001 &
b1 )
b0 5
b1 6
b0 ,
b1 /
b1 0
b10 9
b11001 :
b11000 %
#25000
b1000000000000000000000000100000000000000010000000000000000000000000000000000000000000000000000000000000000000000000000000000000101 "
b1000000000000000000000000100000000000000010000000000000000000000000000000000000000000000000000000000000000000000000000000000000101 '
b11010 #
b11010 &
b10 *
b0 (
b0 )
b1 5
b1 7
b0 6
b0 /
b0 0
b101 9
b11010 :
b11001 %
#26000
b1000000001000000000000001000000000000000000000000000000000000000010000000000000000000000000000000000000000000000000000000000001000 "
b1000000001000000000000001000000000000000000000000000000000000000010000000000000000000000000000000000000000000000000000000000001000 '
b11011 #
b11011 &
b1 (
b10 5
b0 7
b1 ,
b1000 9
b11011 :
b11010 %
#27000
b1000000000000000100000000000000000000000000000000100000001000000000000000000000000000000000000000000000010000000000000000000000011 "
b1000000000000000100000000000000000000000000000000100000001000000000000000000000000000000000000000000000010000000000000000000000011 '
b11100 #
b11100 &
b0 (
b10 )
b0 5
b1 8
b1 6
b0 ,
b10 2
b11 9
b11100 :
b11011 %
#28000
0!
b0 "
b0 '
b0 #
b0 &
b11100 %
#29000
0!
b11101 #
b11101 &
b11101 %
#30000
b11110 %
